pymetric/__init__.py
pymetric/_version.py
pymetric/containers.py
pymetric/_typing/__init__.py
pymetric/_typing/_generic.py
pymetric/coordinates/__init__.py
pymetric/coordinates/_exceptions.py
pymetric/coordinates/base.py
pymetric/coordinates/coordinate_systems.py
pymetric/coordinates/core.py
pymetric/coordinates/mixins/__init__.py
pymetric/coordinates/mixins/_typing.py
pymetric/coordinates/mixins/coords.py
pymetric/coordinates/mixins/core.py
pymetric/coordinates/mixins/mathops.py
pymetric/differential_geometry/__init__.py
pymetric/differential_geometry/dense_ops.py
pymetric/differential_geometry/dense_utils.py
pymetric/differential_geometry/dependence.py
pymetric/differential_geometry/general_ops.py
pymetric/differential_geometry/sparse_ops.py
pymetric/differential_geometry/sparse_utils.py
pymetric/differential_geometry/symbolic.py
pymetric/fields/__init__.py
pymetric/fields/base.py
pymetric/fields/components.py
pymetric/fields/tensors.py
pymetric/fields/buffers/__init__.py
pymetric/fields/buffers/base.py
pymetric/fields/buffers/core.py
pymetric/fields/buffers/registry.py
pymetric/fields/buffers/utilities.py
pymetric/fields/mixins/__init__.py
pymetric/fields/mixins/_generic.py
pymetric/fields/mixins/_typing.py
pymetric/fields/mixins/base.py
pymetric/fields/mixins/components.py
pymetric/fields/mixins/dense_mathops.py
pymetric/fields/utils/__init__.py
pymetric/fields/utils/_typing.py
pymetric/fields/utils/utilities.py
pymetric/grids/__init__.py
pymetric/grids/base.py
pymetric/grids/core.py
pymetric/grids/mixins/__init__.py
pymetric/grids/mixins/_typing.py
pymetric/grids/mixins/chunking.py
pymetric/grids/mixins/core.py
pymetric/grids/mixins/mathops.py
pymetric/grids/utils/__init__.py
pymetric/grids/utils/_exceptions.py
pymetric/grids/utils/_typing.py
pymetric/utilities/__init__.py
pymetric/utilities/arrays.py
pymetric/utilities/config.py
pymetric/utilities/logging.py
pymetric/utilities/symbolic.py
pymetric_lib-0.0.3a2.dev0.dist-info/licenses/LICENSE
pymetric_lib-0.0.3a2.dev0.dist-info/METADATA
pymetric_lib-0.0.3a2.dev0.dist-info/WHEEL
pymetric_lib-0.0.3a2.dev0.dist-info/top_level.txt
pymetric_lib-0.0.3a2.dev0.dist-info/RECORD
